log_configurator/__init__.py
log_configurator/configurator.py
log_configurator/file_log_formatter.py
log_configurator/py.typed
log_configurator/shell_log_formatter.py
log_configurator-0.0.3.dist-info/LICENSE
log_configurator-0.0.3.dist-info/METADATA
log_configurator-0.0.3.dist-info/WHEEL
log_configurator-0.0.3.dist-info/RECORD
