Metadata-Version: 2.3
Name: log-configurator
Version: 0.0.3
Summary: simple tool to facilitate logging - made for my personal use
Author: rlipperts
Author-email: rlipperts@techfak.uni-bielefeld.de
Requires-Python: >=3.12,<4.0
Classifier: Programming Language :: Python :: 3
Classifier: Programming Language :: Python :: 3.12
Classifier: Programming Language :: Python :: 3.13
